{
    "losses":"select  * from v_loses",
    "analitic":"select  * from V_SKLAD_ANALITIC_2",
    "loss-cost":"losses.up_losses_cost",
    "arrived": "select * from VIEW_PRIHOD",
    "test" : "select * from monitoring.get_loses_analitic",
    "get_losses" : "select * from monitoring.GET_LOSSES ",
    "get_storage": "select * from monitoring.get_in_storage",
    "get_arrived": "select * from monitoring.get_arrived",
    "GET_DETDOC": "select * from monitoring.GET_DETDOC_SERIALS(:doc_id,:tov_id,0,:doc_type_id)"
}